CardGame/__init__.py
CardGame/Blackjack/__init__.py
CardGame/Blackjack/game.py
CardGame/Blackjack/money.py
CardGame/Blackjack/person.py
CardGame/Cards/__init__.py
CardGame/Cards/card.py
CardGame/Cards/deck.py
CardGame/Cards/hand.py
dealerschoice-1.0.2.dist-info/LICENSE
dealerschoice-1.0.2.dist-info/METADATA
dealerschoice-1.0.2.dist-info/WHEEL
dealerschoice-1.0.2.dist-info/top_level.txt
dealerschoice-1.0.2.dist-info/RECORD
